tianxiadatong_wx_robot/WX_robot.cp312-win_amd64.pyd
tianxiadatong_wx_robot/config.cp312-win_amd64.pyd
tianxiadatong_wx_robot/config.json
tianxiadatong_wx_robot/db.cp312-win_amd64.pyd
tianxiadatong_wx_robot/model.cp312-win_amd64.pyd
tianxiadatong_wx_robot/models.cp312-win_amd64.pyd
tianxiadatong_wx_robot/robot.cp312-win_amd64.pyd
tianxiadatong_wx_robot/wxauto/__init__.cp312-win_amd64.pyd
tianxiadatong_wx_robot/wxauto/__init__.py
tianxiadatong_wx_robot/wxauto/exceptions.cp312-win_amd64.pyd
tianxiadatong_wx_robot/wxauto/languages.cp312-win_amd64.pyd
tianxiadatong_wx_robot/wxauto/logger.cp312-win_amd64.pyd
tianxiadatong_wx_robot/wxauto/param.cp312-win_amd64.pyd
tianxiadatong_wx_robot/wxauto/uiautomation.py
tianxiadatong_wx_robot/wxauto/wx.cp312-win_amd64.pyd
tianxiadatong_wx_robot/wxauto/msgs/__init__.cp312-win_amd64.pyd
tianxiadatong_wx_robot/wxauto/msgs/__init__.py
tianxiadatong_wx_robot/wxauto/msgs/attr.cp312-win_amd64.pyd
tianxiadatong_wx_robot/wxauto/msgs/base.cp312-win_amd64.pyd
tianxiadatong_wx_robot/wxauto/msgs/friend.cp312-win_amd64.pyd
tianxiadatong_wx_robot/wxauto/msgs/msg.cp312-win_amd64.pyd
tianxiadatong_wx_robot/wxauto/msgs/self.cp312-win_amd64.pyd
tianxiadatong_wx_robot/wxauto/msgs/type.cp312-win_amd64.pyd
tianxiadatong_wx_robot/wxauto/ui/__init__.cp312-win_amd64.pyd
tianxiadatong_wx_robot/wxauto/ui/__init__.py
tianxiadatong_wx_robot/wxauto/ui/base.cp312-win_amd64.pyd
tianxiadatong_wx_robot/wxauto/ui/chatbox.cp312-win_amd64.pyd
tianxiadatong_wx_robot/wxauto/ui/component.cp312-win_amd64.pyd
tianxiadatong_wx_robot/wxauto/ui/main.cp312-win_amd64.pyd
tianxiadatong_wx_robot/wxauto/ui/navigationbox.cp312-win_amd64.pyd
tianxiadatong_wx_robot/wxauto/ui/sessionbox.cp312-win_amd64.pyd
tianxiadatong_wx_robot/wxauto/utils/__init__.cp312-win_amd64.pyd
tianxiadatong_wx_robot/wxauto/utils/__init__.py
tianxiadatong_wx_robot/wxauto/utils/tools.cp312-win_amd64.pyd
tianxiadatong_wx_robot/wxauto/utils/win32.cp312-win_amd64.pyd
tianxiadatong_wx_robot-0.0.8.dist-info/METADATA
tianxiadatong_wx_robot-0.0.8.dist-info/WHEEL
tianxiadatong_wx_robot-0.0.8.dist-info/top_level.txt
tianxiadatong_wx_robot-0.0.8.dist-info/RECORD
